fost_authn_debug
fost_authn
