Metadata-Version: 1.1
Name: django-fost-authn
Version: 0.3.7
Summary: HTTP SHA1 HMAC authentication backend for Django
Home-page: https://github.com/Felspar/django-fost-authn
Author: Kirit Saelensminde
Author-email: kirit@felspar.com
License: Boost Software License - Version 1.0 - August 17th, 2003
Keywords: django authentication hmac sha1 fost
Platform: UNKNOWN
Classifier: Development Status :: 3 - Alpha
Classifier: Framework :: Django
Classifier: Intended Audience :: Developers
Classifier: Programming Language :: Python
Classifier: Topic :: Software Development :: Libraries :: Python Modules
Classifier: License :: OSI Approved
